{"reg": [40, 200, 40, 255], "choice": [0, 110, 12, 255], "disabled": [60, 60, 60, 255], "speech_annoying": [45, 61, 0, 255], "speech_angry": [168, 8, 0, 255], "speech_normal": [95, 255, 95, 255], "speech_sinister": [75, 30, 130, 255], "speech_godlike": [255, 255, 66, 255], "speech_shifty": [89, 97, 143, 255], "speech_driven": [38, 78, 224, 255], "fight": [146, 28, 28, 255], "open": [12, 182, 191, 255], "character": [53, 129, 252, 255], "item": [179, 120, 10, 255], "adjective": [179, 120, 10, 255], "town": [12, 182, 191, 255], "dungeon": [12, 182, 191, 255], "tavern": [12, 182, 191, 255], "shop": [12, 182, 191, 255], "school": [12, 182, 191, 255], "church": [12, 182, 191, 255]}